protein_bert_pytorch/__init__.py
protein_bert_pytorch/protein_bert_pytorch.py
protein_bert_pytorch-0.1.0.dist-info/LICENSE
protein_bert_pytorch-0.1.0.dist-info/METADATA
protein_bert_pytorch-0.1.0.dist-info/WHEEL
protein_bert_pytorch-0.1.0.dist-info/top_level.txt
protein_bert_pytorch-0.1.0.dist-info/RECORD
